{
    "5464dc11-5c3c-4be9-be72-bda895422ea7": {
        "id": "5464dc11-5c3c-4be9-be72-bda895422ea7",
        "name": "Google Search",
        "keyword": "g",
        "cmd": "https://google.com/search?q=%s",
        "icon": "/usr/share/ulauncher/media/google-search-icon.png",
        "is_default_search": true,
        "run_without_argument": false,
        "added": 1630807627.0808787
    },
    "8911102d-0e5d-442e-9a3a-e6ea96ef30a5": {
        "id": "8911102d-0e5d-442e-9a3a-e6ea96ef30a5",
        "name": "Stack Overflow",
        "keyword": "so",
        "cmd": "http://stackoverflow.com/search?q=%s",
        "icon": "/usr/share/ulauncher/media/stackoverflow-icon.svg",
        "is_default_search": true,
        "run_without_argument": false,
        "added": 1630807627.0808966
    },
    "213c547f-cd68-43f9-952a-a5257d585d89": {
        "id": "213c547f-cd68-43f9-952a-a5257d585d89",
        "name": "Wikipedia",
        "keyword": "wiki",
        "cmd": "https://en.wikipedia.org/wiki/%s",
        "icon": "/usr/share/ulauncher/media/wikipedia-icon.png",
        "is_default_search": true,
        "run_without_argument": false,
        "added": 1630807627.080906
    }
}