{"preventUpnDetectSso":false,"silentUpdateTriggered":false,"featureLaunchInfo":{"enableUpnSilentSignin":-1},"previousCrashesInfo":{"crashes":[]},"windowState":{"monitorId":1,"x":3466,"y":78,"width":1868,"height":976,"isMaximized":false,"isFullScreen":false},"surfaceHubWindowState":{"monitorId":-1,"x":0,"y":0,"width":400,"height":600,"isMaximized":true,"isFullScreen":false},"restartCommand":{},"upnWindowUserUpn":"anton.maxen@learnet.se","userUpn":"","userOid":"c76e8296-dc57-41c2-997f-26fdf558c6f1","userTid":"575945ce-2ee0-4503-ba90-6fb4a03b8c30","guestTenantId":"","homeTenantId":"","webAccountId":"","webAccountProviderType":"","launchTime":"1633535316539","desktopZoomLevelV2":3,"guestTenantIds":{},"userAccounts":{},"signedInActiveUser":{},"tidOidMap":{},"isAppFirstRun":false,"upnScreenShowCount":0,"desktopSessionId":"desktop-d552aa12-0324-40a6-a789-24489885c671","teamsUrlProtocolsRegistered":false,"lyncUrlProtocolsRegistered":false,"disableWarningOnOpenKeyRegistered":false,"previousElectronVersion":"10.4.5","lastKnownElectronVersion":"10.4.5","signInRestrictionsLicenseType":"Student","machineId":"9a93a4da4418759d9bf02f662e6851ddcff697af1fac6c73dd3b8e0226aefe20","deviceInfoId":"7716e6f1ec4ab54d2317891b43d7b108028eadf690205eba92788283733e8734","appPreferenceSettings":{"disableGpu":false,"forceRendererAccessibility":false,"openAtLogin":false,"openAsHidden":false,"runningOnClose":true,"registerAsIMProvider":false},"currentWebLanguage":"en-US","isForeground":false,"previousWebClientVersion":"41/1.0.0.2021091540","isLoggedOut":false,"notificationWindowOnClose":true}